bin/tsvtable.py
mdtables/__init__.py
venv/bin/activate_this.py
mdtables-1.1.0.dist-info/LICENSE
mdtables-1.1.0.dist-info/METADATA
mdtables-1.1.0.dist-info/WHEEL
mdtables-1.1.0.dist-info/entry_points.txt
mdtables-1.1.0.dist-info/top_level.txt
mdtables-1.1.0.dist-info/RECORD
