Metadata-Version: 2.1
Name: mdtables
Version: 1.1.0
Summary: Python 3 library to create properly aligned Markdown tables
Author-email: Midgard <noreply@example.org>
Project-URL: Homepage, https://framagit.org/Midgard/python-mdtables
Project-URL: Source, https://framagit.org/Midgard/python-mdtables
Project-URL: Change log, https://framagit.org/Midgard/python-mdtables/-/blob/master/CHANGELOG.md
Project-URL: Bug tracker, https://framagit.org/Midgard/python-mdtables/-/issues
Classifier: Programming Language :: Python :: 3
Classifier: License :: OSI Approved :: GNU General Public License v3 or later (GPLv3+)
Classifier: Operating System :: OS Independent
Classifier: Development Status :: 5 - Production/Stable
Requires-Python: >=3.7
License-File: LICENSE
